rattifyapi/__init__.py
rattifyapi/base.py
rattifyapi/generic.py
rattifyapi/rattify.py
rattifyapi/users.py
rattifyapi-0.2.2.dist-info/LICENSE
rattifyapi-0.2.2.dist-info/METADATA
rattifyapi-0.2.2.dist-info/WHEEL
rattifyapi-0.2.2.dist-info/top_level.txt
rattifyapi-0.2.2.dist-info/RECORD
