Metadata-Version: 2.1
Name: rattifyapi
Version: 0.2.2
Summary: A python library to consume Rattify API
Home-page: https://github.com/ktechhub/rattifyapi
Author: KtechHub
Author-email: info@ktechhub.com
License: MIT
Keywords: rattify rattifyapi python library
Classifier: Intended Audience :: Developers
Classifier: License :: OSI Approved :: MIT License
Classifier: Programming Language :: Python :: 3
Classifier: Programming Language :: Python :: 3.8
Classifier: Programming Language :: Python :: 3.9
Classifier: Programming Language :: Python :: 3.10
Requires-Python: >=3.8.0
License-File: LICENSE
Requires-Dist: requests
Provides-Extra: test
Requires-Dist: coverage ; extra == 'test'
